mlcalcdriver/__init__.py
mlcalcdriver/globals.py
mlcalcdriver/base/__init__.py
mlcalcdriver/base/job.py
mlcalcdriver/base/posinp.py
mlcalcdriver/calculators/__init__.py
mlcalcdriver/calculators/calculator.py
mlcalcdriver/calculators/ensemble.py
mlcalcdriver/calculators/schnetpack.py
mlcalcdriver/calculators/schnetpack_patch.py
mlcalcdriver/calculators/utils.py
mlcalcdriver/calculators/ase_calculators/__init__.py
mlcalcdriver/calculators/ase_calculators/asespkcalculator.py
mlcalcdriver/interfaces/__init__.py
mlcalcdriver/interfaces/ase_interface.py
mlcalcdriver/interfaces/atoms_to_patches.py
mlcalcdriver/interfaces/schnetpack_interface.py
mlcalcdriver/workflows/__init__.py
mlcalcdriver/workflows/geopt.py
mlcalcdriver/workflows/phonon.py
mlcalcdriver-1.4.2.dist-info/LICENSE
mlcalcdriver-1.4.2.dist-info/METADATA
mlcalcdriver-1.4.2.dist-info/WHEEL
mlcalcdriver-1.4.2.dist-info/top_level.txt
mlcalcdriver-1.4.2.dist-info/RECORD
