Metadata-Version: 2.1
Name: mlcalcdriver
Version: 1.4.2
Summary: A package to drive atomic calculations using machine learned models.
Home-page: https://github.com/OMalenfantThuot/ML_Calc_Driver
Author: Olivier Malenfant-Thuot
Author-email: malenfantthuotolivier@gmail.com
License: UNKNOWN
Platform: UNKNOWN
Classifier: Programming Language :: Python :: 3.10
Requires-Dist: numpy (<1.24,>=1.20)
Requires-Dist: torch (>=2.0.1)
Requires-Dist: schnetpack (==1.0.1)
Requires-Dist: ase (>=3.22.0)
